pyresid/__init__.py
pyresid/PDB/FTP_pending.list
pyresid/PDB/FTP_source.idx
pyresid/PDB/PDBID.list
pyresid/PDB/pdb_uniprot_map.pkl
pyresid-0.6.0.dist-info/DESCRIPTION.rst
pyresid-0.6.0.dist-info/METADATA
pyresid-0.6.0.dist-info/RECORD
pyresid-0.6.0.dist-info/WHEEL
pyresid-0.6.0.dist-info/metadata.json
pyresid-0.6.0.dist-info/top_level.txt
