Metadata-Version: 2.0
Name: pyresid
Version: 0.6.0
Summary: Python tools for mining Protein Residuals from Fulltext articles using PMC number, ePMC and PDB
Home-page: UNKNOWN
Author: Rob Firth
Author-email: robert.firth@stfc.ac.uk
License: UNKNOWN
Platform: UNKNOWN
Requires-Dist: bs4
Requires-Dist: scipy
Requires-Dist: numpy
Requires-Dist: matplotlib
Requires-Dist: spacy
Requires-Dist: lxml
Requires-Dist: biopython
Requires-Dist: pycifrw
Requires-Dist: fuzzywuzzy
Requires-Dist: python-Levenshtein
